paqueteoptimizacionelizabeth/__init__.py
paqueteoptimizacionelizabeth/funciones/__init__.py
paqueteoptimizacionelizabeth/funciones/funcionesobjetivo.py
paqueteoptimizacionelizabeth/multivariable/__init__.py
paqueteoptimizacionelizabeth/multivariable/metodosdirectos/__init__.py
paqueteoptimizacionelizabeth/multivariable/metodosdirectos/colina.py
paqueteoptimizacionelizabeth/multivariable/metodosdirectos/hookejeeves.py
paqueteoptimizacionelizabeth/multivariable/metodosdirectos/neldermeadsimplex.py
paqueteoptimizacionelizabeth/multivariable/metodosdirectos/randomwalk.py
paqueteoptimizacionelizabeth/multivariable/metodosdirectos/recocido.py
paqueteoptimizacionelizabeth/multivariable/metodosgradiente/__init__.py
paqueteoptimizacionelizabeth/multivariable/metodosgradiente/cauchy.py
paqueteoptimizacionelizabeth/multivariable/metodosgradiente/gradienteconjugado.py
paqueteoptimizacionelizabeth/multivariable/metodosgradiente/newton.py
paqueteoptimizacionelizabeth/univariable/__init__.py
paqueteoptimizacionelizabeth/univariable/metodosbasadosenladerivada/__init__.py
paqueteoptimizacionelizabeth/univariable/metodosbasadosenladerivada/biseccion.py
paqueteoptimizacionelizabeth/univariable/metodosbasadosenladerivada/newton.py
paqueteoptimizacionelizabeth/univariable/metodosbasadosenladerivada/secante.py
paqueteoptimizacionelizabeth/univariable/metodoseliminacionderegiones/__init__.py
paqueteoptimizacionelizabeth/univariable/metodoseliminacionderegiones/bounding.py
paqueteoptimizacionelizabeth/univariable/metodoseliminacionderegiones/exhaustiva.py
paqueteoptimizacionelizabeth/univariable/metodoseliminacionderegiones/fibonacci.py
paqueteoptimizacionelizabeth/univariable/metodoseliminacionderegiones/golden.py
paqueteoptimizacionelizabeth/univariable/metodoseliminacionderegiones/intervalhalving.py
paqueteoptimizacionelizabeth/utils/__init__.py
paqueteoptimizacionelizabeth/utils/graficas.py
paqueteoptimizacionelizabeth-0.0.1.dist-info/METADATA
paqueteoptimizacionelizabeth-0.0.1.dist-info/WHEEL
paqueteoptimizacionelizabeth-0.0.1.dist-info/top_level.txt
paqueteoptimizacionelizabeth-0.0.1.dist-info/RECORD
